pyatlan/__init__.py
pyatlan/errors.py
pyatlan/logging.conf
pyatlan/multipart_data_generator.py
pyatlan/py.typed
pyatlan/utils.py
pyatlan/version.txt
pyatlan/cache/__init__.py
pyatlan/cache/abstract_asset_cache.py
pyatlan/cache/atlan_tag_cache.py
pyatlan/cache/connection_cache.py
pyatlan/cache/custom_metadata_cache.py
pyatlan/cache/dq_template_config_cache.py
pyatlan/cache/enum_cache.py
pyatlan/cache/group_cache.py
pyatlan/cache/role_cache.py
pyatlan/cache/source_tag_cache.py
pyatlan/cache/user_cache.py
pyatlan/cache/aio/__init__.py
pyatlan/cache/aio/abstract_asset_cache.py
pyatlan/cache/aio/atlan_tag_cache.py
pyatlan/cache/aio/connection_cache.py
pyatlan/cache/aio/custom_metadata_cache.py
pyatlan/cache/aio/dq_template_config_cache.py
pyatlan/cache/aio/enum_cache.py
pyatlan/cache/aio/group_cache.py
pyatlan/cache/aio/role_cache.py
pyatlan/cache/aio/source_tag_cache.py
pyatlan/cache/aio/user_cache.py
pyatlan/cache/common/__init__.py
pyatlan/cache/common/atlan_tag_cache.py
pyatlan/cache/common/custom_metadata_cache.py
pyatlan/cache/common/dq_template_config_cache.py
pyatlan/cache/common/enum_cache.py
pyatlan/cache/common/group_cache.py
pyatlan/cache/common/role_cache.py
pyatlan/cache/common/user_cache.py
pyatlan/client/__init__.py
pyatlan/client/admin.py
pyatlan/client/asset.py
pyatlan/client/atlan.py
pyatlan/client/audit.py
pyatlan/client/constants.py
pyatlan/client/contract.py
pyatlan/client/credential.py
pyatlan/client/file.py
pyatlan/client/group.py
pyatlan/client/impersonate.py
pyatlan/client/oauth.py
pyatlan/client/oauth_client.py
pyatlan/client/open_lineage.py
pyatlan/client/protocol.py
pyatlan/client/query.py
pyatlan/client/role.py
pyatlan/client/search_log.py
pyatlan/client/sso.py
pyatlan/client/task.py
pyatlan/client/token.py
pyatlan/client/transport.py
pyatlan/client/typedef.py
pyatlan/client/user.py
pyatlan/client/workflow.py
pyatlan/client/aio/__init__.py
pyatlan/client/aio/admin.py
pyatlan/client/aio/asset.py
pyatlan/client/aio/atlan.py
pyatlan-8.4.6.dist-info/licenses/LICENSE
pyatlan-8.4.6.dist-info/licenses/NOTICE
pyatlan-8.4.6.dist-info/METADATA
pyatlan-8.4.6.dist-info/WHEEL
pyatlan-8.4.6.dist-info/top_level.txt
pyatlan-8.4.6.dist-info/RECORD
