Metadata-Version: 2.4
Name: pyatlan
Version: 8.4.6
Summary: Atlan Python Client
Author-email: Atlan Technologies Pvt Ltd <engineering@atlan.com>
Maintainer-email: Atlan Technologies Pvt Ltd <engineering@atlan.com>
License: Apache LICENSE 2.0
Project-URL: Homepage, https://github.com/atlanhq/atlan-python
Project-URL: Repository, https://github.com/atlanhq/atlan-python
Project-URL: Documentation, https://github.com/atlanhq/atlan-python
Project-URL: Issues, https://github.com/atlanhq/atlan-python/issues
Keywords: atlan,client
Classifier: Programming Language :: Python :: 3.9
Classifier: Programming Language :: Python :: 3.10
Classifier: Programming Language :: Python :: 3.11
Classifier: Programming Language :: Python :: 3.12
Classifier: Programming Language :: Python :: 3.13
Classifier: License :: OSI Approved :: Apache Software License
Classifier: Operating System :: OS Independent
Classifier: Development Status :: 5 - Production/Stable
Requires-Python: >=3.9
License-File: LICENSE
License-File: NOTICE
Requires-Dist: pydantic~=2.12.4
Requires-Dist: jinja2~=3.1.6
Requires-Dist: tenacity~=9.1.2
Requires-Dist: lazy-loader~=0.4
Requires-Dist: nanoid~=2.0.0
Requires-Dist: pytz~=2025.2
Requires-Dist: python-dateutil~=2.9.0.post0
Requires-Dist: PyYAML~=6.0.3
Requires-Dist: httpx~=0.28.1
Requires-Dist: httpx-retries~=0.4.5
Requires-Dist: authlib~=1.6.5
Dynamic: license-file
